README.rst
setup.py
data_type_tools/__init__.py
data_type_tools.egg-info/PKG-INFO
data_type_tools.egg-info/SOURCES.txt
data_type_tools.egg-info/dependency_links.txt
data_type_tools.egg-info/top_level.txt
data_type_tools/dictionaries/__init__.py
data_type_tools/dictionaries/converters/__init__.py
data_type_tools/dictionaries/converters/converters.py
data_type_tools/dictionaries/mergers/__init__.py
data_type_tools/dictionaries/sorters/__init__.py
data_type_tools/shared/__init__.py
data_type_tools/shared/converters/__init__.py
data_type_tools/shared/converters/interfaces.py