Metadata-Version: 1.0
Name: data-type-tools
Version: 2.0.0
Summary: A collection of tools for working with native Python data types e.x. dictionaries, lists.
Home-page: https://github.com/eddiehowell/python-packages-data_type_tools.git
Author: Eddie Jonathan Howell
Author-email: UNKNOWN
License: UNKNOWN
Keywords: datatypes
Platform: UNKNOWN
